[
  {
    "beta": 0.064431027108818,
    "se": 0.07217757012678516,
    "pval": 0.37203187522548486,
    "ci_lo": -0.07703701033968093,
    "ci_hi": 0.20589906455731694,
    "n": 2039,
    "n_treated": 962,
    "n_control": 1077,
    "n_clusters": 440,
    "r2": 0.12786854483345778,
    "status": "not_sig",
    "se_type": "cluster",
    "outcome": "d_employed",
    "event": "A",
    "event_label": "Event A: 2015\u21922016  MW S/750\u2192S/850  (+13.3%)",
    "event_type": "treatment",
    "band": "narrow",
    "n_cohorts": 4,
    "elasticity": 0.5147763597826449
  },
  {
    "beta": 0.12480110175026275,
    "se": 0.11481382944276862,
    "pval": 0.2770427023128027,
    "ci_lo": -0.10023400395756372,
    "ci_hi": 0.34983620745808924,
    "n": 2039,
    "n_treated": 962,
    "n_control": 1077,
    "n_clusters": 440,
    "r2": 0.02087841175038918,
    "status": "not_sig",
    "se_type": "cluster",
    "outcome": "d_formal",
    "event": "A",
    "event_label": "Event A: 2015\u21922016  MW S/750\u2192S/850  (+13.3%)",
    "event_type": "treatment",
    "band": "narrow",
    "n_cohorts": 4,
    "elasticity": 0.99710744556905
  },
  {
    "beta": 0.07983842976783108,
    "se": 0.11110176683417587,
    "pval": 0.47238352956987173,
    "ci_lo": -0.1379210332271536,
    "ci_hi": 0.2975978927628158,
    "n": 1321,
    "n_treated": 665,
    "n_control": 656,
    "n_clusters": 283,
    "r2": 0.002285987157475855,
    "status": "not_sig",
    "se_type": "cluster",
    "outcome": "d_log_wage_stayers",
    "event": "A",
    "event_label": "Event A: 2015\u21922016  MW S/750\u2192S/850  (+13.3%)",
    "event_type": "treatment",
    "band": "narrow",
    "n_cohorts": 4,
    "elasticity": 0.6378749197530899
  }
]